chaise/__init__.py
chaise/attrs.py
chaise/cli/__init__.py
chaise/cli/__main__.py
chaise/cli/client.py
chaise/cli/datafiles.py
chaise/dictful.py
chaise/helpers.py
chaise/structs.py
chaise-0.6.0.dist-info/METADATA
chaise-0.6.0.dist-info/WHEEL
chaise-0.6.0.dist-info/entry_points.txt
chaise-0.6.0.dist-info/RECORD
